{
  "scan_info": {
    "timestamp": "2025-07-10T21:55:46.647397",
    "repository_root": "/home/runner/work/metro-ai-rpg/metro-ai-rpg",
    "total_files_checked": 59,
    "total_directories_scanned": 21,
    "total_violations": 48,
    "master_index_loaded": true
  },
  "compliance_status": {
    "overall": "FAIL",
    "high_severity_issues": 0,
    "medium_severity_issues": 0,
    "low_severity_issues": 48
  },
  "violations": [
    {
      "rule": "pep8_compliance",
      "type": "line_too_long",
      "severity": "low",
      "file": "system/todo/repo_rule_checker.py",
      "line": 139,
      "message": "Line 139 exceeds 79 characters (80 chars)"
    },
    {
      "rule": "pep8_compliance",
      "type": "line_too_long",
      "severity": "low",
      "file": "system/todo/repo_rule_checker.py",
      "line": 187,
      "message": "Line 187 exceeds 79 characters (83 chars)"
    },
    {
      "rule": "pep8_compliance",
      "type": "line_too_long",
      "severity": "low",
      "file": "system/todo/repo_rule_checker.py",
      "line": 237,
      "message": "Line 237 exceeds 79 characters (90 chars)"
    },
    {
      "rule": "pep8_compliance",
      "type": "line_too_long",
      "severity": "low",
      "file": "system/todo/repo_rule_checker.py",
      "line": 247,
      "message": "Line 247 exceeds 79 characters (81 chars)"
    },
    {
      "rule": "pep8_compliance",
      "type": "line_too_long",
      "severity": "low",
      "file": "system/todo/repo_rule_checker.py",
      "line": 258,
      "message": "Line 258 exceeds 79 characters (82 chars)"
    },
    {
      "rule": "pep8_compliance",
      "type": "line_too_long",
      "severity": "low",
      "file": "system/todo/repo_rule_checker.py",
      "line": 259,
      "message": "Line 259 exceeds 79 characters (97 chars)"
    },
    {
      "rule": "pep8_compliance",
      "type": "line_too_long",
      "severity": "low",
      "file": "system/todo/repo_rule_checker.py",
      "line": 323,
      "message": "Line 323 exceeds 79 characters (90 chars)"
    },
    {
      "rule": "pep8_compliance",
      "type": "line_too_long",
      "severity": "low",
      "file": "system/todo/repo_rule_checker.py",
      "line": 332,
      "message": "Line 332 exceeds 79 characters (81 chars)"
    },
    {
      "rule": "pep8_compliance",
      "type": "line_too_long",
      "severity": "low",
      "file": "system/todo/repo_rule_checker.py",
      "line": 333,
      "message": "Line 333 exceeds 79 characters (86 chars)"
    },
    {
      "rule": "pep8_compliance",
      "type": "line_too_long",
      "severity": "low",
      "file": "system/todo/repo_rule_checker.py",
      "line": 350,
      "message": "Line 350 exceeds 79 characters (90 chars)"
    },
    {
      "rule": "pep8_compliance",
      "type": "line_too_long",
      "severity": "low",
      "file": "system/todo/repo_rule_checker.py",
      "line": 355,
      "message": "Line 355 exceeds 79 characters (86 chars)"
    },
    {
      "rule": "pep8_compliance",
      "type": "line_too_long",
      "severity": "low",
      "file": "system/todo/repo_rule_checker.py",
      "line": 363,
      "message": "Line 363 exceeds 79 characters (85 chars)"
    },
    {
      "rule": "pep8_compliance",
      "type": "line_too_long",
      "severity": "low",
      "file": "system/todo/repo_rule_checker.py",
      "line": 366,
      "message": "Line 366 exceeds 79 characters (106 chars)"
    },
    {
      "rule": "pep8_compliance",
      "type": "line_too_long",
      "severity": "low",
      "file": "system/todo/repo_rule_checker.py",
      "line": 378,
      "message": "Line 378 exceeds 79 characters (106 chars)"
    },
    {
      "rule": "pep8_compliance",
      "type": "line_too_long",
      "severity": "low",
      "file": "system/todo/repo_rule_checker.py",
      "line": 398,
      "message": "Line 398 exceeds 79 characters (98 chars)"
    },
    {
      "rule": "pep8_compliance",
      "type": "line_too_long",
      "severity": "low",
      "file": "system/todo/repo_rule_checker.py",
      "line": 426,
      "message": "Line 426 exceeds 79 characters (85 chars)"
    },
    {
      "rule": "pep8_compliance",
      "type": "line_too_long",
      "severity": "low",
      "file": "system/todo/repo_rule_checker.py",
      "line": 431,
      "message": "Line 431 exceeds 79 characters (99 chars)"
    },
    {
      "rule": "pep8_compliance",
      "type": "line_too_long",
      "severity": "low",
      "file": "system/todo/repo_rule_checker.py",
      "line": 471,
      "message": "Line 471 exceeds 79 characters (112 chars)"
    },
    {
      "rule": "pep8_compliance",
      "type": "line_too_long",
      "severity": "low",
      "file": "system/todo/repo_rule_checker.py",
      "line": 482,
      "message": "Line 482 exceeds 79 characters (89 chars)"
    },
    {
      "rule": "pep8_compliance",
      "type": "line_too_long",
      "severity": "low",
      "file": "system/todo/repo_rule_checker.py",
      "line": 493,
      "message": "Line 493 exceeds 79 characters (85 chars)"
    },
    {
      "rule": "pep8_compliance",
      "type": "line_too_long",
      "severity": "low",
      "file": "system/todo/repo_rule_checker.py",
      "line": 502,
      "message": "Line 502 exceeds 79 characters (82 chars)"
    },
    {
      "rule": "pep8_compliance",
      "type": "line_too_long",
      "severity": "low",
      "file": "system/todo/repo_rule_checker.py",
      "line": 511,
      "message": "Line 511 exceeds 79 characters (82 chars)"
    },
    {
      "rule": "pep8_compliance",
      "type": "line_too_long",
      "severity": "low",
      "file": "system/todo/repo_rule_checker.py",
      "line": 512,
      "message": "Line 512 exceeds 79 characters (83 chars)"
    },
    {
      "rule": "pep8_compliance",
      "type": "line_too_long",
      "severity": "low",
      "file": "system/todo/repo_rule_checker.py",
      "line": 531,
      "message": "Line 531 exceeds 79 characters (116 chars)"
    },
    {
      "rule": "pep8_compliance",
      "type": "line_too_long",
      "severity": "low",
      "file": "system/todo/repo_rule_checker.py",
      "line": 532,
      "message": "Line 532 exceeds 79 characters (80 chars)"
    },
    {
      "rule": "pep8_compliance",
      "type": "line_too_long",
      "severity": "low",
      "file": "system/todo/repo_rule_checker.py",
      "line": 540,
      "message": "Line 540 exceeds 79 characters (135 chars)"
    },
    {
      "rule": "pep8_compliance",
      "type": "line_too_long",
      "severity": "low",
      "file": "system/todo/repo_rule_checker.py",
      "line": 591,
      "message": "Line 591 exceeds 79 characters (88 chars)"
    },
    {
      "rule": "pep8_compliance",
      "type": "line_too_long",
      "severity": "low",
      "file": "system/todo/repo_rule_checker.py",
      "line": 618,
      "message": "Line 618 exceeds 79 characters (102 chars)"
    },
    {
      "rule": "pep8_compliance",
      "type": "line_too_long",
      "severity": "low",
      "file": "system/todo/repo_rule_checker.py",
      "line": 619,
      "message": "Line 619 exceeds 79 characters (106 chars)"
    },
    {
      "rule": "pep8_compliance",
      "type": "line_too_long",
      "severity": "low",
      "file": "system/todo/repo_rule_checker.py",
      "line": 620,
      "message": "Line 620 exceeds 79 characters (99 chars)"
    },
    {
      "rule": "pep8_compliance",
      "type": "line_too_long",
      "severity": "low",
      "file": "system/todo/repo_rule_checker.py",
      "line": 622,
      "message": "Line 622 exceeds 79 characters (97 chars)"
    },
    {
      "rule": "pep8_compliance",
      "type": "line_too_long",
      "severity": "low",
      "file": "system/todo/repo_rule_checker.py",
      "line": 650,
      "message": "Line 650 exceeds 79 characters (89 chars)"
    },
    {
      "rule": "pep8_compliance",
      "type": "line_too_long",
      "severity": "low",
      "file": "system/todo/repo_rule_checker.py",
      "line": 663,
      "message": "Line 663 exceeds 79 characters (89 chars)"
    },
    {
      "rule": "pep8_compliance",
      "type": "line_too_long",
      "severity": "low",
      "file": "system/todo/repo_rule_checker.py",
      "line": 681,
      "message": "Line 681 exceeds 79 characters (82 chars)"
    },
    {
      "rule": "pep8_compliance",
      "type": "line_too_long",
      "severity": "low",
      "file": "system/todo/repo_rule_checker.py",
      "line": 682,
      "message": "Line 682 exceeds 79 characters (86 chars)"
    },
    {
      "rule": "pep8_compliance",
      "type": "line_too_long",
      "severity": "low",
      "file": "system/todo/repo_rule_checker.py",
      "line": 736,
      "message": "Line 736 exceeds 79 characters (83 chars)"
    },
    {
      "rule": "pep8_compliance",
      "type": "line_too_long",
      "severity": "low",
      "file": "system/todo/repo_rule_checker.py",
      "line": 737,
      "message": "Line 737 exceeds 79 characters (85 chars)"
    },
    {
      "rule": "pep8_compliance",
      "type": "line_too_long",
      "severity": "low",
      "file": "system/todo/repo_rule_checker.py",
      "line": 747,
      "message": "Line 747 exceeds 79 characters (85 chars)"
    },
    {
      "rule": "pep8_compliance",
      "type": "line_too_long",
      "severity": "low",
      "file": "system/todo/repo_rule_checker.py",
      "line": 749,
      "message": "Line 749 exceeds 79 characters (81 chars)"
    },
    {
      "rule": "pep8_compliance",
      "type": "line_too_long",
      "severity": "low",
      "file": "system/todo/repo_rule_checker.py",
      "line": 768,
      "message": "Line 768 exceeds 79 characters (93 chars)"
    },
    {
      "rule": "pep8_compliance",
      "type": "line_too_long",
      "severity": "low",
      "file": "system/todo/repo_rule_checker.py",
      "line": 784,
      "message": "Line 784 exceeds 79 characters (118 chars)"
    },
    {
      "rule": "pep8_compliance",
      "type": "line_too_long",
      "severity": "low",
      "file": "system/todo/repo_rule_checker.py",
      "line": 786,
      "message": "Line 786 exceeds 79 characters (83 chars)"
    },
    {
      "rule": "pep8_compliance",
      "type": "line_too_long",
      "severity": "low",
      "file": "system/todo/repo_rule_checker.py",
      "line": 787,
      "message": "Line 787 exceeds 79 characters (92 chars)"
    },
    {
      "rule": "pep8_compliance",
      "type": "line_too_long",
      "severity": "low",
      "file": "system/todo/repo_rule_checker.py",
      "line": 797,
      "message": "Line 797 exceeds 79 characters (93 chars)"
    },
    {
      "rule": "pep8_compliance",
      "type": "line_too_long",
      "severity": "low",
      "file": "system/todo/repo_rule_checker.py",
      "line": 805,
      "message": "Line 805 exceeds 79 characters (85 chars)"
    },
    {
      "rule": "pep8_compliance",
      "type": "line_too_long",
      "severity": "low",
      "file": "system/todo/repo_rule_checker.py",
      "line": 811,
      "message": "Line 811 exceeds 79 characters (80 chars)"
    },
    {
      "rule": "pep8_compliance",
      "type": "line_too_long",
      "severity": "low",
      "file": "system/todo/update_master_index.py",
      "line": 237,
      "message": "Line 237 exceeds 79 characters (84 chars)"
    },
    {
      "rule": "pep8_compliance",
      "type": "line_too_long",
      "severity": "low",
      "file": "system/todo/update_master_index.py",
      "line": 245,
      "message": "Line 245 exceeds 79 characters (93 chars)"
    }
  ],
  "violation_summary": {
    "pep8_compliance": {
      "total": 48,
      "high": 0,
      "medium": 0,
      "low": 48
    }
  }
}